<?xml version="1.0" encoding="utf-8"?>
<files>
  <keys type="item" key="FM_000_0009" value="Pergaminho de Familiar Comum" />
  <keys type="item" key="FM_000_0011" value="Pergaminho de Familiar de Elite" />
  <keys type="item" key="FM_000_0012" value="Pergaminho de Familiar Heroico" />
  <keys type="item" key="FM_000_0013" value="Pergaminho de Familiar Lendário" />
  <keys type="item" key="FM_000_0010" value="Item de Conversão de Pet (Teste)" />
  <keys type="item" key="SF1_1_000_0003" value="Pedra-Lacre Heroica de Exarahn" />
  <keys type="item" key="IT_FE_UF_0000" value="Pedra de Deslacre Elite" />
  <keys type="item" key="IT_FE_UF_0001" value="Pedra de Deslacre Heroica" />
  <keys type="item" key="CA_FE_UF_0000" value="Pedra de Deslacre Elite" />
  <keys type="item" key="CA_FE_UF_0001" value="Pedra de Deslacre Heroica" />
  <keys type="item" key="IT_FE_EF_0000" value="Extrator de Pedra-Lacre Elite" />
  <keys type="item" key="IT_FE_EF_0001" value="Extrator de Pedra-Lacre Elite de Stygaea" />
  <keys type="item" key="IT_FE_EF_0002" value="Extrator de Pedra-Lacre Elite III" />
  <keys type="item" key="IT_FE_EF_0003" value="Extrator de Pedra-Lacre Elite IV" />
  <keys type="item" key="IT_FE_EF_0004" value="Extrator de Pedra-Lacre Elite V" />
  <keys type="item" key="IT_FE_EF_0005" value="Extrator de Pedra-Lacre Heroica" />
  <keys type="item" key="IT_FE_EF_0006" value="Extrator de Pedra-Lacre Heroica de Stygaea" />
  <keys type="item" key="IT_FE_EF_0007" value="Extrator de Pedra-Lacre Heroica III" />
  <keys type="item" key="IT_FE_EF_0008" value="Extrator de Pedra-Lacre Heroica IV" />
  <keys type="item" key="IT_FE_EF_0009" value="Extrator de Pedra-Lacre Heroica V" />
  <keys type="item" key="CA_FE_EF_0000" value="Extrator de Pedra-Lacre Elite Abençoado" />
  <keys type="item" key="CA_FE_EF_0001" value="Extrator de Pedra-Lacre Elite II" />
  <keys type="item" key="CA_FE_EF_0002" value="Extrator de Pedra-Lacre Elite III" />
  <keys type="item" key="CA_FE_EF_0003" value="Extrator de Pedra-Lacre Elite IV" />
  <keys type="item" key="CA_FE_EF_0004" value="Extrator de Pedra-Lacre Heroica" />
  <keys type="item" key="CA_FE_EF_0005" value="Extrator de Pedra-Lacre Heroica Abençoado" />
  <keys type="item" key="CA_FE_EF_0006" value="Extrator de Pedra-Lacre Heroica II" />
  <keys type="item" key="CA_FE_EF_0007" value="Extrator de Pedra-Lacre Heroica III" />
  <keys type="item" key="CA_FE_EF_0008" value="Extrator de Pedra-Lacre Heroica IV" />
  <keys type="item" key="CA_FE_EF_0009" value="Extrator de Pedra-Lacre Lendária" />
  <keys type="item" key="CA_FE_EF_0010" value="Extrator de Pedra-Lacre Lendária Abençoado" />
  <keys type="item" key="CA_FE_FB_0098" value="Ração de Provisão (1 hora)" />
  <keys type="item" key="CA_FE_FB_0099" value="Ração de Provisão (3 horas)" />
  <keys type="item" key="CA_FE_FB_0100" value="Ração de Provisão (6 horas)" />
  <keys type="item" key="CA_FE_FB_0101" value="Ração de Provisão (12 horas)" />
  <keys type="item" key="CA_FE_FB_0000" value="Ração Premium (1 hora)" />
  <keys type="item" key="CA_FE_FB_0001" value="Ração Premium (6 horas)" />
  <keys type="item" key="CA_FE_FB_0002" value="Ração Premium (12 horas)" />
  <keys type="item" key="CA_FE_FB_0003" value="Ração Suprema (1 hora)" />
  <keys type="item" key="CA_FE_FB_0004" value="Ração Suprema (6 horas)" />
  <keys type="item" key="CA_FE_FB_0005" value="Ração Suprema (12 horas)" />
  <keys type="item" key="IT_FE_TS_0001" value="Teste de Extração de Pedra-Lacre (Elite)" />
  <keys type="item" key="IT_FE_TS_0002" value="Teste de Extração de Pedra-Lacre (Elite)" />
  <keys type="item" key="IT_FE_TS_0003" value="Teste de Extração de Pedra-Lacre (Elite)" />
  <keys type="item" key="IT_FE_TS_0004" value="Teste de Extração de Pedra-Lacre (+1)" />
  <keys type="item" key="IT_FE_TS_0005" value="Teste de Extração de Pedra-Lacre (+2)" />
  <keys type="item" key="IT_FE_TS_0006" value="Teste de Extração de Pedra-Lacre (+3)" />
  <keys type="item" key="IT_FE_TS_0007" value="Teste de Extração de Pedra-Lacre (+4)" />
  <keys type="item" key="IT_FE_TS_0008" value="Teste de Extração de Pedra-Lacre (+5)" />
  <keys type="item" key="SF1_1_000_0004" value="Pedra-Lacre Comum Nível 60" />
  <keys type="item" key="IT_FE_EF_0010" value="Extrator de Pedra-Lacre Lendária" />
  <keys type="item" key="CA_FE_ES_0000" value="Ferramenta Teste de Gravar Familiar (1 min)" />
  <keys type="item" key="CA_FE_ES_0001" value="Ferramenta Teste de Gravar Familiar (10 min)" />
  <keys type="item" key="IT_FE_ES_0000" value="Cinzel de Familiares (1 dia)" />
  <keys type="item" key="IT_FE_ES_0001" value="Cinzel de Familiares (7 dias)" />
  <keys type="item" key="IT_FE_ES_0002" value="Cinzel de Familiares (15 dias)" />
  <keys type="item" key="IT_FE_ES_0003" value="Cinzel de Familiares (30 dias)" />
  <keys type="item" key="CA_FE_EM_0000" value="Extrator de Pedra-Lacre Heroica +5" />
  <keys type="item" key="CA_FE_EM_0001" value="Extrator de Pedra-Lacre Lendária +5" />
  <keys type="item" key="CA_FE_EM_0002" value="Extrator de Pedra-Lacre Heroica +5" />
  <keys type="item" key="CA_FE_EM_0003" value="Extrator de Pedra-Lacre Lendária +5" />
  <keys type="item" key="FM_000_0017" value="Pergaminho de Familiar Comum" />
  <keys type="item" key="FM_000_0018" value="Pergaminho de Familiar de Elite" />
  <keys type="item" key="FM_000_0019" value="Pergaminho de Familiar Heroico" />
  <keys type="item" key="FM_000_0020" value="Pergaminho de Familiar Lendário" />
  <keys type="item" key="SF1_4_001_0000" value="Pedra-Lacre Lendária" />
  <keys type="item" key="PvP_CO_FE_0001" value="Extrator de Pedra-Lacre Lendária" />
  <keys type="item" key="FI_FE_EM_0001" value="Extrator de Pedra-Lacre Heroica +5" />
  <keys type="item" key="FI_FE_EM_0002" value="Extrator de Pedra-Lacre Lendária +5" />
  <keys type="item" key="IT_FE_EF_0011" value="Extrator de Pedra-Lacre Lendária +5" />
  <keys type="item" key="CA_FE_EM_0004" value="Extrator de Pedra-Lacre Heroica +7" />
  <keys type="item" key="CA_FE_EM_0005" value="Extrator de Pedra-Lacre Lendária +7" />
  <keys type="item" key="CA_FE_EM_0006" value="Extrator de Pedra-Lacre Heroica +7" />
  <keys type="item" key="CA_FE_EM_0007" value="Extrator de Pedra-Lacre Lendária +7" />
  <keys type="item" key="CA_FE_EM_0008" value="Extrator de Pedra-Lacre Heroica +6" />
  <keys type="item" key="CA_FE_EM_0009" value="Extrator de Pedra-Lacre Lendária +6" />
  <keys type="item" key="CA_FE_EM_0010" value="Extrator de Pedra-Lacre Heroica +6" />
  <keys type="item" key="CA_FE_EM_0011" value="Extrator de Pedra-Lacre Lendária +6" />
  <keys type="item" key="TS_FA_FB_0999" value="Impulsionador de Aventura de Familiar (Teste)" />
  <keys type="item" key="PvP_CO_FE_0002" value="Extrator Lendário +5" />
  <keys type="item" key="CA_FE_FB_0008" value="Impulsionador da Evolução (1 hora)" />
  <keys type="item" key="CA_FE_FB_0009" value="Impulsionador da Evolução (3 horas)" />
  <keys type="item" key="CA_FE_FB_0010" value="Impulsionador da Evolução (6 horas)" />
  <keys type="item" key="IT_FE_EF_0012" value="Extrator de Pedra-Lacre Lendária" />
  <keys type="item" key="SF1_4_000_0103" value="Pedra-Lacre Lendária" />
  <keys type="item" key="EV_FE_FC_0001" value="Pergaminho de Reiniciar Coleção de Familiar" />
  <keys type="item" key="IT_FA_FB_0001" value="Adventure Booster (10%)" />
  <keys type="item" key="IT_FA_FB_0002" value="Adventure Booster (30%)" />
  <keys type="item" key="IT_FA_FB_0003" value="Adventure Booster (35%)" />
  <keys type="item" key="IT_FA_FB_0004" value="Adventure Booster (45%)" />
  <keys type="item" key="IT_FA_FB_0005" value="Adventure Booster (50%)" />
  <keys type="item" key="IT_FA_FB_0006" value="Adventure Booster (100%)" />
  <keys type="item" key="IT_FE_FB_0000" value="Growth booster (2 hours)" />
  <keys type="item" key="IT_FE_FB_0001" value="High-Speed Growth Booster (2 hours)" />
  <keys type="item" key="IT_FE_CA_0004" value="Cartão de Captura" />
  <keys type="item" key="IT_FE_CA_0005" value="Cartão de Captura Brilhante" />
  <keys type="item" key="IT_FE_CA_0006" value="Cartão de Captura Predestinada" />
  <keys type="item" key="IT_FE_CA_0007" value="Cartão de captura Para Prática" />
  <keys type="item" key="IT_FE_CA_0008" value="Cartão de Captura Predestinada" />
  <keys type="item" key="FM_000_0002_1" value="Heroic Pet Scroll" />
  <keys type="item" key="IT_FE_CA_0009" value="Cartão de Captura Brilhante" />
  <keys type="item" key="CA_FE_EM_0101" value="Mythic Extractor" />
  <keys type="item" key="CA_FE_EM_0102" value="+5 Enhanced Mythic Extractor" />
  <keys type="item" key="CA_FE_EM_0103" value="+6 Enhanced Mythic Extractor" />
  <keys type="item" key="CA_FE_EM_0104" value="+7 Enhanced Mythic Extractor" />
  <keys type="item" key="FM_000_0111" value="Mythic Fellow Order" />
  <keys type="item" key="FM_000_0112" value="Mythic Pet Order" />
  <keys type="item" key="SF1_7_000_0000" value="Mythic Sealing Stone" />
  <keys type="item" key="IT_FE_CA_0101" value="Mythic Capture Card" />
</files>